{
  "project_info": {
    "project_number": "392955523631",
    "project_id": "capgemini-asturias-pablo",
    "storage_bucket": "capgemini-asturias-pablo.appspot.com"
  },
  "client": [
    {
      "client_info": {
        "mobilesdk_app_id": "1:392955523631:android:a7379d15764d36a6d30cda",
        "android_client_info": {
          "package_name": "com.asturias.capgemini"
        }
      },
      "oauth_client": [],
      "api_key": [
        {
          "current_key": "AIzaSyAEJ-k61bwoy_8JkYCSoq96g9Eh8p8QnKc"
        }
      ],
      "services": {
        "appinvite_service": {
          "other_platform_oauth_client": []
        }
      }
    }
  ],
  "configuration_version": "1"
}